[
  {
    "no": 1,
    "title": "111",
    "content": "111",
    "writer": "111",
    "password": "111",
    "viewCount": 1,
    "createdDate": 1688379578133
  },
  {
    "no": 3,
    "title": "ㅋㅋㅋ",
    "content": "ㅋㅋㅋㅋㅋㅋㅋㅋㅋㅋㅋ",
    "writer": "하하하",
    "password": "1111",
    "viewCount": 0,
    "createdDate": 1688622410677
  },
  {
    "no": 4,
    "title": "ㅇㅇㅇㅇ",
    "content": "2222",
    "writer": "ㅂㅈㄷㅂㅈㄷ",
    "password": "123123",
    "viewCount": 0,
    "createdDate": 1688622428006
  }
]